{
  "meta": {
    "id": "abashiri",
    "name": "網走市",
    "pref": "北海道",
    "lat": 44.02,
    "lon": 144.2697
  },
  "current": {
    "time": "2026-01-22T11:15",
    "interval": 900,
    "temperature_2m": -5.8,
    "weather_code": 3
  },
  "daily": {
    "time": [
      "2026-01-22",
      "2026-01-23",
      "2026-01-24",
      "2026-01-25",
      "2026-01-26",
      "2026-01-27",
      "2026-01-28"
    ],
    "weather_code": [
      71,
      3,
      2,
      73,
      71,
      71,
      71
    ],
    "temperature_2m_max": [
      -4.9,
      -3.4,
      -5.1,
      -5.5,
      -4.6,
      -4.2,
      -4.3
    ],
    "temperature_2m_min": [
      -8.2,
      -9.9,
      -12.1,
      -10.9,
      -8.7,
      -10.4,
      -9.1
    ]
  },
  "updatedAt": "2026-01-22T02:29:21.759Z"
}