{
  "meta": {
    "id": "fukuoka",
    "name": "福岡市",
    "pref": "福岡県",
    "lat": 33.58333,
    "lon": 130.39999
  },
  "current": {
    "time": "2026-04-21T05:45",
    "interval": 900,
    "temperature_2m": 14.3,
    "weather_code": 1
  },
  "daily": {
    "time": [
      "2026-04-21",
      "2026-04-22",
      "2026-04-23",
      "2026-04-24",
      "2026-04-25",
      "2026-04-26",
      "2026-04-27"
    ],
    "weather_code": [
      3,
      61,
      63,
      2,
      0,
      3,
      51
    ],
    "temperature_2m_max": [
      17.9,
      16.9,
      15.3,
      19.4,
      21.7,
      22.6,
      20.4
    ],
    "temperature_2m_min": [
      14.1,
      12.3,
      13.9,
      11.7,
      10.2,
      10.1,
      14
    ]
  },
  "updatedAt": "2026-04-20T20:54:40.147Z"
}