{
  "meta": {
    "id": "fukuoka",
    "name": "福岡市",
    "pref": "福岡県",
    "lat": 33.58333,
    "lon": 130.39999
  },
  "current": {
    "time": "2026-06-15T09:15",
    "interval": 900,
    "temperature_2m": 21.5,
    "weather_code": 2
  },
  "daily": {
    "time": [
      "2026-06-15",
      "2026-06-16",
      "2026-06-17",
      "2026-06-18",
      "2026-06-19",
      "2026-06-20",
      "2026-06-21"
    ],
    "weather_code": [
      51,
      3,
      3,
      53,
      51,
      55,
      63
    ],
    "temperature_2m_max": [
      25.7,
      26.3,
      27.9,
      27,
      28.3,
      26.7,
      27.6
    ],
    "temperature_2m_min": [
      20,
      21.3,
      21.9,
      23.6,
      24.1,
      24.6,
      23.4
    ]
  },
  "updatedAt": "2026-06-15T00:17:31.178Z"
}