{
  "meta": {
    "id": "hakodate",
    "name": "函館市",
    "pref": "北海道",
    "lat": 41.7687,
    "lon": 140.7288
  },
  "current": {
    "time": "2025-11-18T22:45",
    "interval": 900,
    "temperature_2m": 1.1,
    "weather_code": 0
  },
  "daily": {
    "time": [
      "2025-11-18",
      "2025-11-19",
      "2025-11-20",
      "2025-11-21",
      "2025-11-22",
      "2025-11-23",
      "2025-11-24"
    ],
    "weather_code": [
      53,
      51,
      53,
      2,
      2,
      51,
      53
    ],
    "temperature_2m_max": [
      3.2,
      6.6,
      12.9,
      11.9,
      4.4,
      10.6,
      11.6
    ],
    "temperature_2m_min": [
      0.8,
      1.2,
      6.9,
      1,
      0.9,
      4.6,
      8.6
    ]
  },
  "updatedAt": "2025-11-18T13:55:06.142Z"
}