{
  "meta": {
    "id": "hakodate",
    "name": "函館市",
    "pref": "北海道",
    "lat": 41.7687,
    "lon": 140.7288
  },
  "current": {
    "time": "2025-11-13T00:15",
    "interval": 900,
    "temperature_2m": 8.9,
    "weather_code": 0
  },
  "daily": {
    "time": [
      "2025-11-13",
      "2025-11-14",
      "2025-11-15",
      "2025-11-16",
      "2025-11-17",
      "2025-11-18",
      "2025-11-19"
    ],
    "weather_code": [
      53,
      1,
      1,
      53,
      71,
      71,
      71
    ],
    "temperature_2m_max": [
      14,
      8.8,
      8.8,
      10.8,
      11.4,
      -0.1,
      4.4
    ],
    "temperature_2m_min": [
      8.8,
      4.4,
      0.1,
      -0.1,
      -0.9,
      -2.6,
      -2.5
    ]
  },
  "updatedAt": "2025-11-12T15:28:04.681Z"
}