{
  "meta": {
    "id": "hakodate",
    "name": "函館市",
    "pref": "北海道",
    "lat": 41.7687,
    "lon": 140.7288
  },
  "current": {
    "time": "2026-02-21T01:45",
    "interval": 900,
    "temperature_2m": 6.3,
    "weather_code": 2
  },
  "daily": {
    "time": [
      "2026-02-21",
      "2026-02-22",
      "2026-02-23",
      "2026-02-24",
      "2026-02-25",
      "2026-02-26",
      "2026-02-27"
    ],
    "weather_code": [
      3,
      2,
      51,
      71,
      2,
      3,
      51
    ],
    "temperature_2m_max": [
      8.5,
      10.1,
      11.1,
      0.7,
      1.7,
      3.4,
      3.1
    ],
    "temperature_2m_min": [
      4.5,
      7.1,
      0.5,
      -3.2,
      -3.9,
      -2.5,
      1.8
    ]
  },
  "updatedAt": "2026-02-20T16:49:09.185Z"
}