{
  "meta": {
    "id": "hiroshima",
    "name": "広島市",
    "pref": "広島県",
    "lat": 34.39161,
    "lon": 132.45182
  },
  "current": {
    "time": "2026-04-03T18:30",
    "interval": 900,
    "temperature_2m": 16.3,
    "weather_code": 3
  },
  "daily": {
    "time": [
      "2026-04-03",
      "2026-04-04",
      "2026-04-05",
      "2026-04-06",
      "2026-04-07",
      "2026-04-08",
      "2026-04-09"
    ],
    "weather_code": [
      3,
      65,
      3,
      3,
      51,
      1,
      51
    ],
    "temperature_2m_max": [
      19.1,
      18.9,
      20.7,
      21.1,
      22.1,
      18,
      18.8
    ],
    "temperature_2m_min": [
      7.3,
      12.3,
      11,
      8.6,
      10.3,
      8.1,
      7
    ]
  },
  "updatedAt": "2026-04-03T09:38:41.376Z"
}