{
  "meta": {
    "id": "hiroshima",
    "name": "広島市",
    "pref": "広島県",
    "lat": 34.39161,
    "lon": 132.45182
  },
  "current": {
    "time": "2026-06-22T09:15",
    "interval": 900,
    "temperature_2m": 23.4,
    "weather_code": 2
  },
  "daily": {
    "time": [
      "2026-06-22",
      "2026-06-23",
      "2026-06-24",
      "2026-06-25",
      "2026-06-26",
      "2026-06-27",
      "2026-06-28"
    ],
    "weather_code": [
      53,
      3,
      53,
      63,
      51,
      53,
      61
    ],
    "temperature_2m_max": [
      23.5,
      25.9,
      23.6,
      22.8,
      26.8,
      27.8,
      25.1
    ],
    "temperature_2m_min": [
      19.9,
      19.5,
      19.4,
      19.2,
      20,
      18.5,
      22.2
    ]
  },
  "updatedAt": "2026-06-22T00:16:10.846Z"
}