{
  "meta": {
    "id": "hiroshima",
    "name": "広島市",
    "pref": "広島県",
    "lat": 34.39161,
    "lon": 132.45182
  },
  "current": {
    "time": "2026-06-20T05:15",
    "interval": 900,
    "temperature_2m": 22.6,
    "weather_code": 61
  },
  "daily": {
    "time": [
      "2026-06-20",
      "2026-06-21",
      "2026-06-22",
      "2026-06-23",
      "2026-06-24",
      "2026-06-25",
      "2026-06-26"
    ],
    "weather_code": [
      65,
      3,
      3,
      3,
      55,
      63,
      51
    ],
    "temperature_2m_max": [
      24.3,
      25.7,
      27.7,
      25.9,
      22.7,
      23.7,
      29.9
    ],
    "temperature_2m_min": [
      22.6,
      21.7,
      21.7,
      19.3,
      18.2,
      19.3,
      22.1
    ]
  },
  "updatedAt": "2026-06-19T20:16:01.765Z"
}