{
  "meta": {
    "id": "kumamoto",
    "name": "熊本市",
    "pref": "熊本県",
    "lat": 32.8031,
    "lon": 130.7079
  },
  "current": {
    "time": "2026-04-21T07:45",
    "interval": 900,
    "temperature_2m": 15.4,
    "weather_code": 1
  },
  "daily": {
    "time": [
      "2026-04-21",
      "2026-04-22",
      "2026-04-23",
      "2026-04-24",
      "2026-04-25",
      "2026-04-26",
      "2026-04-27"
    ],
    "weather_code": [
      2,
      55,
      65,
      1,
      1,
      51,
      53
    ],
    "temperature_2m_max": [
      24.3,
      20,
      18.5,
      19.3,
      22.9,
      20.8,
      20.7
    ],
    "temperature_2m_min": [
      13.6,
      12.1,
      14.3,
      12.1,
      10.4,
      13.2,
      16.2
    ]
  },
  "updatedAt": "2026-04-20T22:51:11.874Z"
}