{
  "meta": {
    "id": "kushiro",
    "name": "釧路市",
    "pref": "北海道",
    "lat": 42.9849,
    "lon": 144.3819
  },
  "current": {
    "time": "2025-12-28T23:45",
    "interval": 900,
    "temperature_2m": -5.7,
    "weather_code": 0
  },
  "daily": {
    "time": [
      "2025-12-28",
      "2025-12-29",
      "2025-12-30",
      "2025-12-31",
      "2026-01-01",
      "2026-01-02",
      "2026-01-03"
    ],
    "weather_code": [
      0,
      53,
      53,
      3,
      0,
      71,
      71
    ],
    "temperature_2m_max": [
      -1.1,
      5.5,
      5.3,
      -0.9,
      -5.7,
      -3.5,
      -2.5
    ],
    "temperature_2m_min": [
      -6.6,
      -7.2,
      -2.5,
      -5.2,
      -7.5,
      -8.1,
      -6.4
    ]
  },
  "updatedAt": "2025-12-28T14:56:42.428Z"
}