{
  "meta": {
    "id": "kushiro",
    "name": "釧路市",
    "pref": "北海道",
    "lat": 42.9849,
    "lon": 144.3819
  },
  "current": {
    "time": "2026-02-05T06:45",
    "interval": 900,
    "temperature_2m": -6.4,
    "weather_code": 0
  },
  "daily": {
    "time": [
      "2026-02-05",
      "2026-02-06",
      "2026-02-07",
      "2026-02-08",
      "2026-02-09",
      "2026-02-10",
      "2026-02-11"
    ],
    "weather_code": [
      2,
      75,
      2,
      2,
      2,
      2,
      71
    ],
    "temperature_2m_max": [
      -0.8,
      2.3,
      -5.1,
      -5.1,
      -4.7,
      -0.9,
      2.7
    ],
    "temperature_2m_min": [
      -6.4,
      -6.4,
      -9.2,
      -10.6,
      -12,
      -8.2,
      -3
    ]
  },
  "updatedAt": "2026-02-04T21:54:14.718Z"
}