{
  "meta": {
    "id": "kushiro",
    "name": "釧路市",
    "pref": "北海道",
    "lat": 42.9849,
    "lon": 144.3819
  },
  "current": {
    "time": "2026-01-24T18:45",
    "interval": 900,
    "temperature_2m": -5.2,
    "weather_code": 0
  },
  "daily": {
    "time": [
      "2026-01-24",
      "2026-01-25",
      "2026-01-26",
      "2026-01-27",
      "2026-01-28",
      "2026-01-29",
      "2026-01-30"
    ],
    "weather_code": [
      1,
      2,
      2,
      71,
      71,
      2,
      0
    ],
    "temperature_2m_max": [
      -3,
      -3.9,
      -4.6,
      -3.9,
      -2.2,
      -3,
      -2.4
    ],
    "temperature_2m_min": [
      -10.5,
      -9.7,
      -9.6,
      -12.1,
      -9.1,
      -8.4,
      -9.1
    ]
  },
  "updatedAt": "2026-01-24T09:46:23.559Z"
}