{
  "meta": {
    "id": "miyazaki",
    "name": "宮崎市",
    "pref": "宮崎県",
    "lat": 31.90778,
    "lon": 131.42028
  },
  "current": {
    "time": "2025-10-02T22:45",
    "interval": 900,
    "temperature_2m": 23.5,
    "weather_code": 1
  },
  "daily": {
    "time": [
      "2025-10-02",
      "2025-10-03",
      "2025-10-04",
      "2025-10-05",
      "2025-10-06",
      "2025-10-07",
      "2025-10-08"
    ],
    "weather_code": [
      2,
      51,
      53,
      51,
      51,
      2,
      51
    ],
    "temperature_2m_max": [
      26.5,
      25.5,
      30,
      28.8,
      27.2,
      27.7,
      29.4
    ],
    "temperature_2m_min": [
      21.6,
      21.4,
      23.1,
      24.2,
      25.5,
      24.8,
      24.6
    ]
  },
  "updatedAt": "2025-10-02T13:45:36.319Z"
}