{
  "meta": {
    "id": "morioka",
    "name": "盛岡市",
    "pref": "岩手県",
    "lat": 39.7,
    "lon": 141.15
  },
  "current": {
    "time": "2026-04-16T03:45",
    "interval": 900,
    "temperature_2m": 6.3,
    "weather_code": 61
  },
  "daily": {
    "time": [
      "2026-04-16",
      "2026-04-17",
      "2026-04-18",
      "2026-04-19",
      "2026-04-20",
      "2026-04-21",
      "2026-04-22"
    ],
    "weather_code": [
      63,
      3,
      2,
      0,
      2,
      51,
      0
    ],
    "temperature_2m_max": [
      10.7,
      17.8,
      21.2,
      19.8,
      22.8,
      14,
      13.4
    ],
    "temperature_2m_min": [
      4.2,
      0.8,
      5.3,
      8.1,
      7.2,
      7.4,
      7.5
    ]
  },
  "updatedAt": "2026-04-15T18:49:26.329Z"
}