{
  "meta": {
    "id": "morioka",
    "name": "盛岡市",
    "pref": "岩手県",
    "lat": 39.7,
    "lon": 141.15
  },
  "current": {
    "time": "2025-12-29T00:15",
    "interval": 900,
    "temperature_2m": -2.3,
    "weather_code": 0
  },
  "daily": {
    "time": [
      "2025-12-29",
      "2025-12-30",
      "2025-12-31",
      "2026-01-01",
      "2026-01-02",
      "2026-01-03",
      "2026-01-04"
    ],
    "weather_code": [
      61,
      63,
      71,
      71,
      71,
      73,
      71
    ],
    "temperature_2m_max": [
      3.8,
      7.3,
      0.6,
      -4,
      -3.5,
      -4.6,
      -0.7
    ],
    "temperature_2m_min": [
      -3.6,
      0.4,
      -5.6,
      -8.6,
      -8.8,
      -6.2,
      -6.2
    ]
  },
  "updatedAt": "2025-12-28T15:27:21.156Z"
}