{
  "meta": {
    "id": "morioka",
    "name": "盛岡市",
    "pref": "岩手県",
    "lat": 39.7,
    "lon": 141.15
  },
  "current": {
    "time": "2026-01-20T20:00",
    "interval": 900,
    "temperature_2m": -6.4,
    "weather_code": 1
  },
  "daily": {
    "time": [
      "2026-01-20",
      "2026-01-21",
      "2026-01-22",
      "2026-01-23",
      "2026-01-24",
      "2026-01-25",
      "2026-01-26"
    ],
    "weather_code": [
      73,
      71,
      71,
      71,
      71,
      71,
      71
    ],
    "temperature_2m_max": [
      -0.5,
      -2.9,
      -3,
      -1.9,
      -4.1,
      -4.6,
      -3.2
    ],
    "temperature_2m_min": [
      -6.4,
      -9.4,
      -10.3,
      -9.9,
      -13.9,
      -7.5,
      -7.6
    ]
  },
  "updatedAt": "2026-01-20T11:01:04.734Z"
}