{
  "meta": {
    "id": "morioka",
    "name": "盛岡市",
    "pref": "岩手県",
    "lat": 39.7,
    "lon": 141.15
  },
  "current": {
    "time": "2025-10-03T11:45",
    "interval": 900,
    "temperature_2m": 24,
    "weather_code": 0
  },
  "daily": {
    "time": [
      "2025-10-03",
      "2025-10-04",
      "2025-10-05",
      "2025-10-06",
      "2025-10-07",
      "2025-10-08",
      "2025-10-09"
    ],
    "weather_code": [
      3,
      2,
      3,
      51,
      55,
      61,
      2
    ],
    "temperature_2m_max": [
      25.8,
      25.1,
      23.6,
      22.5,
      16.5,
      18.3,
      13.6
    ],
    "temperature_2m_min": [
      12.4,
      13,
      16.4,
      11.1,
      9.4,
      12.8,
      8.8
    ]
  },
  "updatedAt": "2025-10-03T02:46:36.695Z"
}