{
  "meta": {
    "id": "nagoya",
    "name": "名古屋市",
    "pref": "愛知県",
    "lat": 35.18145,
    "lon": 136.9064
  },
  "current": {
    "time": "2025-12-02T23:30",
    "interval": 900,
    "temperature_2m": 10.6,
    "weather_code": 2
  },
  "daily": {
    "time": [
      "2025-12-02",
      "2025-12-03",
      "2025-12-04",
      "2025-12-05",
      "2025-12-06",
      "2025-12-07",
      "2025-12-08"
    ],
    "weather_code": [
      3,
      61,
      61,
      53,
      1,
      0,
      53
    ],
    "temperature_2m_max": [
      18.1,
      12,
      8.1,
      8.6,
      11.4,
      13.5,
      15.1
    ],
    "temperature_2m_min": [
      7.8,
      2.2,
      2,
      3.8,
      2.5,
      3.7,
      5
    ]
  },
  "updatedAt": "2025-12-02T14:33:12.662Z"
}