{
  "meta": {
    "id": "nagoya",
    "name": "名古屋市",
    "pref": "愛知県",
    "lat": 35.18145,
    "lon": 136.9064
  },
  "current": {
    "time": "2025-11-10T23:45",
    "interval": 900,
    "temperature_2m": 9.6,
    "weather_code": 1
  },
  "daily": {
    "time": [
      "2025-11-10",
      "2025-11-11",
      "2025-11-12",
      "2025-11-13",
      "2025-11-14",
      "2025-11-15",
      "2025-11-16"
    ],
    "weather_code": [
      3,
      1,
      2,
      3,
      3,
      1,
      51
    ],
    "temperature_2m_max": [
      16.9,
      17,
      16.6,
      18.7,
      19,
      19,
      20
    ],
    "temperature_2m_min": [
      9.9,
      7.2,
      6.8,
      10.3,
      11.1,
      9.1,
      11.4
    ]
  },
  "updatedAt": "2025-11-10T14:45:54.079Z"
}