{
  "meta": {
    "id": "niigata",
    "name": "新潟市",
    "pref": "新潟県",
    "lat": 37.91611,
    "lon": 139.03639
  },
  "current": {
    "time": "2026-05-10T09:00",
    "interval": 900,
    "temperature_2m": 17.2,
    "weather_code": 0
  },
  "daily": {
    "time": [
      "2026-05-10",
      "2026-05-11",
      "2026-05-12",
      "2026-05-13",
      "2026-05-14",
      "2026-05-15",
      "2026-05-16"
    ],
    "weather_code": [
      0,
      3,
      61,
      53,
      51,
      51,
      51
    ],
    "temperature_2m_max": [
      20,
      23.3,
      22,
      17,
      15.2,
      18.1,
      17.7
    ],
    "temperature_2m_min": [
      11,
      10.8,
      13.2,
      12.5,
      12.6,
      15.3,
      13.3
    ]
  },
  "updatedAt": "2026-05-10T00:05:33.509Z"
}