{
  "meta": {
    "id": "oita",
    "name": "大分市",
    "pref": "大分県",
    "lat": 33.2396,
    "lon": 131.6093
  },
  "current": {
    "time": "2025-10-05T20:30",
    "interval": 900,
    "temperature_2m": 25.4,
    "weather_code": 2
  },
  "daily": {
    "time": [
      "2025-10-05",
      "2025-10-06",
      "2025-10-07",
      "2025-10-08",
      "2025-10-09",
      "2025-10-10",
      "2025-10-11"
    ],
    "weather_code": [
      51,
      2,
      1,
      51,
      51,
      1,
      1
    ],
    "temperature_2m_max": [
      27.5,
      26.4,
      27,
      25.4,
      24.4,
      23.1,
      25.9
    ],
    "temperature_2m_min": [
      24.1,
      23.3,
      22.9,
      21.5,
      16.1,
      13.5,
      12.8
    ]
  },
  "updatedAt": "2025-10-05T11:38:39.957Z"
}