{
  "meta": {
    "id": "osaka",
    "name": "大阪市",
    "pref": "大阪府",
    "lat": 34.69374,
    "lon": 135.50217
  },
  "current": {
    "time": "2026-04-04T18:45",
    "interval": 900,
    "temperature_2m": 15,
    "weather_code": 2
  },
  "daily": {
    "time": [
      "2026-04-04",
      "2026-04-05",
      "2026-04-06",
      "2026-04-07",
      "2026-04-08",
      "2026-04-09",
      "2026-04-10"
    ],
    "weather_code": [
      63,
      3,
      55,
      55,
      51,
      53,
      61
    ],
    "temperature_2m_max": [
      17.5,
      20.2,
      19.9,
      17.9,
      16.7,
      21.4,
      24.1
    ],
    "temperature_2m_min": [
      9.8,
      12.8,
      11.1,
      9.5,
      8.1,
      10.3,
      15.4
    ]
  },
  "updatedAt": "2026-04-04T09:51:07.569Z"
}