{
  "meta": {
    "id": "sendai",
    "name": "仙台市",
    "pref": "宮城県",
    "lat": 38.26884,
    "lon": 140.87194
  },
  "current": {
    "time": "2025-12-08T00:15",
    "interval": 900,
    "temperature_2m": 5.8,
    "weather_code": 1
  },
  "daily": {
    "time": [
      "2025-12-08",
      "2025-12-09",
      "2025-12-10",
      "2025-12-11",
      "2025-12-12",
      "2025-12-13",
      "2025-12-14"
    ],
    "weather_code": [
      51,
      1,
      53,
      51,
      1,
      71,
      63
    ],
    "temperature_2m_max": [
      15.1,
      7.7,
      8.6,
      10.9,
      3.7,
      4.1,
      11
    ],
    "temperature_2m_min": [
      5.7,
      2.5,
      1.2,
      2.4,
      -0.3,
      -0.7,
      2.8
    ]
  },
  "updatedAt": "2025-12-07T15:21:36.732Z"
}